colight/__init__.py
colight/binary_serialization.py
colight/chrome_devtools.py
colight/core.py
colight/env.py
colight/format.py
colight/html.py
colight/inspect.py
colight/layout.py
colight/plot.py
colight/plot_defs.py
colight/plot_extras.py
colight/plot_spec.py
colight/protocols.py
colight/scene3d.py
colight/screenshots.py
colight/server.py
colight/state_operations.py
colight/util.py
colight/widget.py
colight/components/__init__.py
colight/components/bitmap.py
colight/components/slider.py
colight/docs/__init__.py
colight/js-dist/anywidget.mjs
colight/js-dist/embed.js
colight/js-dist/embed.mjs
colight/js-dist/live.js
colight/js-dist/widget.mjs
colight/scripts/css_modifier.py
colight/scripts/make_observable_plot_defs.py
colight/scripts/mkdocs_hooks.py
colight/scripts/observable_plot_metadata.js
colight/scripts/observable_plot_metadata.json
colight/scripts/package.json
colight/scripts/yarn.lock
colight-2025.7.8.dist-info/METADATA
colight-2025.7.8.dist-info/WHEEL
colight-2025.7.8.dist-info/RECORD
