Metadata-Version: 2.4
Name: colight
Version: 2025.7.8
Author-email: Matthew Huebert <me@matt.is>
License: MIT
Requires-Python: >=3.10
Requires-Dist: anywidget>=0.9.10
Requires-Dist: traitlets>=5.14.3
Requires-Dist: websockets>=15.0
